richclub/__init__.py
richclub/rich_club_coefficient_degree.py
richclub/rich_club_coefficient_rank.py
richclub/secord_order_average_degree.py
richclub/secord_order_largest_degree.py
richclubv4-1.0.3.dev1.dist-info/DESCRIPTION.rst
richclubv4-1.0.3.dev1.dist-info/METADATA
richclubv4-1.0.3.dev1.dist-info/RECORD
richclubv4-1.0.3.dev1.dist-info/WHEEL
richclubv4-1.0.3.dev1.dist-info/metadata.json
richclubv4-1.0.3.dev1.dist-info/top_level.txt
